{
    "js": [
        "js/fixedHeader.bootstrap5.js",
        "js/fixedHeader.bootstrap5.min.js",
        "js/fixedHeader.bootstrap5.min.mjs",
        "js/fixedHeader.bootstrap5.mjs"
    ],
    "css": [
        "css/fixedHeader.bootstrap5.css",
        "css/fixedHeader.bootstrap5.min.css"
    ],
    "types": [
        "types/fixedHeader.bootstrap5.d.ts"
    ],
    "src-repo": "http://github.com/DataTables/FixedHeader",
    "last-tag": "4.0.2",
    "last-sync": "5f95cdce65325f15da3b89ed38f9099fa67c6d91"
}